multilogin_python/__init__.py
multilogin_python/client.py
multilogin_python-0.1.1.dist-info/METADATA
multilogin_python-0.1.1.dist-info/WHEEL
multilogin_python-0.1.1.dist-info/RECORD
