Metadata-Version: 2.1
Name: multilogin-python
Version: 0.1.1
Summary: 
Author: Waqar Khan
Author-email: sms.raees@gmail.com
Requires-Python: >=3.10,<4.0
Classifier: Programming Language :: Python :: 3
Classifier: Programming Language :: Python :: 3.10
Classifier: Programming Language :: Python :: 3.11
Requires-Dist: requests (>=2.28.2,<3.0.0)
